README.md
setup.py
pktktimer/__init__.py
pktktimer/pechatimer.py
pktktimer.egg-info/PKG-INFO
pktktimer.egg-info/SOURCES.txt
pktktimer.egg-info/dependency_links.txt
pktktimer.egg-info/entry_points.txt
pktktimer.egg-info/top_level.txt