Metadata-Version: 2.1
Name: pktktimer
Version: 1.0.0
Summary: A more flexible pecha kucha timer
Home-page: https://github.com/eshrh/pktktimer
Author: Eshan Ramesh
Author-email: esrh@netc.eu
License: UNKNOWN
Platform: UNKNOWN
Classifier: Programming Language :: Python :: 3
Classifier: Operating System :: OS Independent
Requires-Python: >=3.6
